lib_one_proto/__init__.py
lib_one_proto/active_sensor_device_pb2.py
lib_one_proto/authorization_operation_type_pb2.py
lib_one_proto/authorization_result_pb2.py
lib_one_proto/battery_low_pb2.py
lib_one_proto/battery_pb2.py
lib_one_proto/battery_update_pb2.py
lib_one_proto/bluetooth_pb2.py
lib_one_proto/bt_central_notification_pb2.py
lib_one_proto/bt_central_pb2.py
lib_one_proto/button_press_params_pb2.py
lib_one_proto/button_press_pb2.py
lib_one_proto/calibrate_gyro_pb2.py
lib_one_proto/camera_live_info_pb2.py
lib_one_proto/camera_live_result_pb2.py
lib_one_proto/camera_posture_pb2.py
lib_one_proto/camera_submode_pb2.py
lib_one_proto/camera_wifi_connection_result_pb2.py
lib_one_proto/cancel_capture_pb2.py
lib_one_proto/cancel_request_authorization_pb2.py
lib_one_proto/capture_auto_split_pb2.py
lib_one_proto/capture_state_pb2.py
lib_one_proto/capture_stopped_pb2.py
lib_one_proto/capture_trigger_source_pb2.py
lib_one_proto/chargebox_pb2.py
lib_one_proto/charging_command_type_pb2.py
lib_one_proto/check_authorization_pb2.py
lib_one_proto/close_camera_oled_pb2.py
lib_one_proto/cloud_storage_pb2.py
lib_one_proto/current_capture_status_pb2.py
lib_one_proto/darkeis_status_pb2.py
lib_one_proto/delete_file_operation_pb2.py
lib_one_proto/delete_files_pb2.py
lib_one_proto/detect_face_pb2.py
lib_one_proto/download_info_pb2.py
lib_one_proto/editinfo_list_pb2.py
lib_one_proto/error_pb2.py
lib_one_proto/exposure_pb2.py
lib_one_proto/exposure_update_pb2.py
lib_one_proto/extra_info_pb2.py
lib_one_proto/file_type_pb2.py
lib_one_proto/fileinfo_list_pb2.py
lib_one_proto/flicker_pb2.py
lib_one_proto/fw_upgrade_state_pb2.py
lib_one_proto/get_button_press_params_pb2.py
lib_one_proto/get_camera_live_info_pb2.py
lib_one_proto/get_cloud_storage_status_pb2.py
lib_one_proto/get_current_button_status_pb2.py
lib_one_proto/get_current_capture_status_pb2.py
lib_one_proto/get_file_extra_pb2.py
lib_one_proto/get_file_finish_pb2.py
lib_one_proto/get_file_list_pb2.py
lib_one_proto/get_file_pb2.py
lib_one_proto-0.1.2.dist-info/METADATA
lib_one_proto-0.1.2.dist-info/WHEEL
lib_one_proto-0.1.2.dist-info/RECORD
