Metadata-Version: 2.1
Name: lib-one-proto
Version: 0.1.2
Summary: Insta360 Proto Buffer files from libOne.so contained into the Android app compiled in python
License: GPL-3.0-or-later
Author: avilabss
Author-email: contact@avilabs.net
Requires-Python: >=3.10.0
Classifier: License :: OSI Approved :: GNU General Public License v3 or later (GPLv3+)
Classifier: Programming Language :: Python :: 3
Classifier: Programming Language :: Python :: 3.10
Classifier: Programming Language :: Python :: 3.11
Classifier: Programming Language :: Python :: 3.12
Requires-Dist: protobuf (>=5.27.3,<6.0.0)
